dev_container_gen/__init__.py
dev_container_gen/dev_container_manager.py
dev_container_gen/loader.py
dev_container_gen/model.py
dev_container_gen/py.typed
dev_container_gen/saver.py
slough/__init__.py
slough/config_file_finder.py
slough/exceptions.py
slough/py.typed
slough/slough.py
slough/storage_manager.py
slough/yaml_storage_manager.py
slough_cli_tool/__init__.py
slough_cli_tool/__main__.py
slough_cli_tool/cli_app.py
slough_cli_tool/cli_context.py
slough_cli_tool/cli_error_handeling.py
slough_cli_tool/cli_output_models.py
slough_cli_tool/cli_output_visitor.py
slough_cli_tool/config.py
slough_cli_tool/container.py
slough_cli_tool/container_platforms.py
slough_cli_tool/container_tags.py
slough_cli_tool/dev_container.py
slough_cli_tool/exceptions.py
slough_cli_tool/main.py
slough_cli_tool/profiles.py
slough_cli_tool/project.py
slough_cli_tool/py.typed
slough_cli_tool-1.0.0b8.dist-info/licenses/LICENSE.md
slough_config/__init__.py
slough_config/config_model.py
slough_config/config_model_visitor.py
slough_config/exceptions.py
slough_config/py.typed
template_engine/__init__.py
template_engine/py.typed
template_engine/template_engine.py
slough_cli_tool-1.0.0b8.dist-info/METADATA
slough_cli_tool-1.0.0b8.dist-info/WHEEL
slough_cli_tool-1.0.0b8.dist-info/entry_points.txt
slough_cli_tool-1.0.0b8.dist-info/top_level.txt
slough_cli_tool-1.0.0b8.dist-info/RECORD
