Metadata-Version: 2.4
Name: slough-cli-tool
Version: 1.0.0b8
Summary: Add your description here
Author-email: Daryl Stark <daryl@dstark.nl>
Requires-Python: >=3.13
License-File: LICENSE.md
Requires-Dist: jinja2>=3.1.6
Requires-Dist: pydantic>=2.10.4
Requires-Dist: pyyaml>=6.0.2
Requires-Dist: typer>=0.15.1
Dynamic: license-file
